handprofiler/__init__.py
handprofiler/__version__.py
handprofiler/profiler.py
handprofiler-0.0.3.dist-info/LICENSE
handprofiler-0.0.3.dist-info/METADATA
handprofiler-0.0.3.dist-info/WHEEL
handprofiler-0.0.3.dist-info/top_level.txt
handprofiler-0.0.3.dist-info/RECORD
