Metadata-Version: 2.1
Name: handprofiler
Version: 0.0.3
Summary: UNKNOWN
Home-page: https://github.com/rilshok/hand-profiler
Author: Vladislav A. Proskurov
Author-email: rilshok@pm.me
License: UNKNOWN
Platform: UNKNOWN
Classifier: Programming Language :: Python :: 3.6
Classifier: License :: OSI Approved :: MIT License
Classifier: Operating System :: OS Independent
Classifier: Development Status :: 1 - Planning
Requires-Python: >=3.6
License-File: LICENSE
